README.rst
setup.py
Flask_Storage_Helpers.egg-info/PKG-INFO
Flask_Storage_Helpers.egg-info/SOURCES.txt
Flask_Storage_Helpers.egg-info/dependency_links.txt
Flask_Storage_Helpers.egg-info/not-zip-safe
Flask_Storage_Helpers.egg-info/requires.txt
Flask_Storage_Helpers.egg-info/top_level.txt
flask_storage_helpers/__init__.py
flask_storage_helpers/amazon.py
flask_storage_helpers/base.py
flask_storage_helpers/cloudfiles.py
flask_storage_helpers/filesystem.py
flask_storage_helpers/mock.py
flask_storage_helpers/utils.py