Metadata-Version: 1.1
Name: Flask-Storage-Helpers
Version: 0.1.5
Summary: Various file storage backends for Flask apps.
Home-page: http://github.com/achauve/flask-storage-helpers
Author: Konsta Vesterinen
Author-email: konsta.vesterinen@gmail.com
License: MIT
Platform: any
Classifier: Development Status :: 4 - Beta
Classifier: Environment :: Web Environment
Classifier: Intended Audience :: Developers
Classifier: License :: OSI Approved :: BSD License
Classifier: Operating System :: OS Independent
Classifier: Programming Language :: Python
Classifier: Topic :: Internet :: WWW/HTTP :: Dynamic Content
Classifier: Topic :: Software Development :: Libraries :: Python Modules
